rai_sam/__init__.py
rai_sam/engine/client/content.py
rai_sam/engine/packager/content.py
rai_sam/engine/packager/vector.py
rai_sam/libs/libsam_client.so
rai_sam/libs/libsam_packager.so
rai_sam-1.0.0.dist-info/LICENSE
rai_sam-1.0.0.dist-info/METADATA
rai_sam-1.0.0.dist-info/WHEEL
rai_sam-1.0.0.dist-info/top_level.txt
rai_sam-1.0.0.dist-info/RECORD
